{
  "__file": "wp_block",
  "title": "Text Design 6",
  "content": "<!-- wp:amp/rowlayout {\"uniqueID\":\"_da2\",\"columns\":1,\"colLayout\":\"equal\",\"topPadding\":70,\"bottomPadding\":40,\"topPaddingM\":30,\"bottomPaddingM\":20,\"leftPaddingM\":15,\"rightPaddingM\":15,\"bgColor\":\"#1a1a1a\",\"blockAlignment\":\"full\",\"tabletPadding\":[30,20,20,20]} -->\n<div class=\"wp-block-amp-rowlayout cr alignfull\"><div id=\"ri_da2\" class=\"ab rb ri_da2\"><div class=\"cw ab1 gd gvd rvtop rlequal tlinherit rmc-left-to-right mrow\"><!-- wp:amp/column {\"uniqueID\":\"_f2b\"} -->\n<div class=\"wp-block-amp-column c c-1 cd_f2b\"><div class=\"ci\"><!-- wp:amp/rowlayout {\"uniqueID\":\"_06d\",\"columns\":1,\"colLayout\":\"equal\",\"maxWidth\":1400} -->\n<div class=\"wp-block-amp-rowlayout cr alignnone\"><div id=\"ri_06d\" class=\"ab  ri_06d\"><div class=\"cw ab1 gd gvd rvtop rlequal tlinherit rmc-left-to-right mrow\"><!-- wp:amp/column {\"uniqueID\":\"_fc0\"} -->\n<div class=\"wp-block-amp-column c c-1 cd_fc0\"><div class=\"ci\"><!-- wp:amp/rowlayout {\"uniqueID\":\"_594\",\"colLayout\":\"equal\",\"topPadding\":0,\"leftPadding\":0,\"rightPadding\":0,\"firstColumnWidth\":55,\"secondColumnWidth\":45} -->\n<div class=\"wp-block-amp-rowlayout cr alignnone\"><div id=\"ri_594\" class=\"ab  ri_594\"><div class=\"cw ab2 gd gvd rvtop rlequal tlinherit rmc-left-to-right mrow amp-custom-first-width-55 amp-custom-second-width-45\"><!-- wp:amp/column {\"uniqueID\":\"_5a0\"} -->\n<div class=\"wp-block-amp-column c c-1 cd_5a0\"><div class=\"ci\"><!-- wp:ampblocks/image {\"width\":512,\"maxwidth\":685,\"height\":446,\"maxheight\":600,\"percentage\":77,\"imageurl\":\"https://raw.githubusercontent.com/jasthilokesh/sampletest/master/images/td6.png\"} -->\n<div class=\"wp-block-ampblocks-image imw\"><div class=\"imc\" style=\"max-width:685px\"><img class=\"im-t\" src=\"https://raw.githubusercontent.com/jasthilokesh/sampletest/master/images/td6.png\" style=\"width:77%\"/></div></div>\n<!-- /wp:ampblocks/image --></div></div>\n<!-- /wp:amp/column -->\n\n<!-- wp:amp/column {\"id\":2,\"leftPadding\":125,\"rightPadding\":125,\"topPaddingM\":0,\"bottomPaddingM\":0,\"leftPaddingM\":0,\"rightPaddingM\":0,\"uniqueID\":\"_8dd\",\"topPaddingT\":0,\"bottomPaddingT\":0,\"leftPaddingT\":25,\"rightPaddingT\":25} -->\n<div class=\"wp-block-amp-column c c-2 cd_8dd\"><div class=\"ci\"><!-- wp:ampblocks/heading {\"uniqueID\":\"_dac\",\"color\":\"#fff\",\"size\":48,\"lineHeight\":62,\"tabSize\":40,\"tabLineHeight\":52,\"mobileSize\":36,\"mobileLineHeight\":44,\"letterSpacing\":0.5,\"typography\":\"Montserrat\",\"googleFont\":true,\"fontSubset\":\"latin\",\"fontVariant\":\"900\",\"fontWeight\":\"900\",\"bottomMargin\":30} -->\n<h2 id=\"h_dac\" class=\"h_dac hp wp-block-amp-advancedheading\" style=\"color:#fff;letter-spacing:0.5px;margin-top:10px;margin-bottom:30px\">Our Values</h2>\n<!-- /wp:ampblocks/heading -->\n\n<!-- wp:amp/advancedheading {\"uniqueID\":\"_b1d\",\"color\":\"#fff\",\"size\":16,\"lineHeight\":26,\"typography\":\"Montserrat\",\"googleFont\":true,\"fontSubset\":\"latin\",\"fontVariant\":\"regular\",\"fontWeight\":\"400\",\"topMargin\":0,\"bottomMargin\":0} -->\n<p id=\"h_b1d\" class=\"h_b1d pp wp-block-amp-advancedheading\" style=\"color:#fff;margin-top:0px;margin-bottom:0px\">Search advertising subconsciously pushes the ad unit. Placement generates a constructive image formation. Market information reinforces targeted traffic, recognizing the social responsibility of business. The marketing tool, analyzing the results of an advertising campaign, spontaneously restores a comprehensive presentation material, recognizing certain market trends. The creative concept is still interesting for many.</p>\n<!-- /wp:amp/advancedheading -->\n\n<!-- wp:amp/rowlayout {\"uniqueID\":\"_022\",\"columns\":1,\"colLayout\":\"equal\",\"currentTab\":\"mobile\",\"bottomPadding\":0,\"leftPadding\":0,\"rightPadding\":0,\"topPaddingM\":20,\"bottomPaddingM\":0,\"leftPaddingM\":0,\"rightPaddingM\":0} -->\n<div class=\"wp-block-amp-rowlayout cr alignnone\"><div id=\"ri_022\" class=\"ab  ri_022\"><div class=\"cw ab1 gd gvd rvtop rlequal tlinherit rmc-left-to-right mrow\"><!-- wp:amp/column {\"topPadding\":20,\"bottomPadding\":20,\"leftPadding\":20,\"rightPadding\":20,\"border\":\"#474747\",\"borderWidth\":[1,1,1,1],\"uniqueID\":\"_5b2\"} -->\n<div class=\"wp-block-amp-column c c-1 cd_5b2\"><div class=\"ci\"><!-- wp:ampblocks/heading {\"uniqueID\":\"_0f0\",\"color\":\"#fff\",\"size\":12,\"lineHeight\":18,\"letterSpacing\":1,\"typography\":\"Montserrat\",\"googleFont\":true,\"fontSubset\":\"latin\",\"fontVariant\":\"700\",\"fontWeight\":\"700\",\"topMargin\":0} -->\n<h2 id=\"h_0f0\" class=\"h_0f0 hp wp-block-amp-advancedheading\" style=\"color:#fff;letter-spacing:1px;margin-top:0px;margin-bottom:10px\">OUR MAIN PRINCIPLE</h2>\n<!-- /wp:ampblocks/heading -->\n\n<!-- wp:amp/advancedheading {\"uniqueID\":\"_17d\",\"color\":\"#fff\",\"size\":14,\"lineHeight\":24,\"typography\":\"Montserrat\",\"googleFont\":true,\"fontSubset\":\"latin\",\"fontVariant\":\"regular\",\"fontWeight\":\"400\",\"bottomMargin\":0} -->\n<p id=\"h_17d\" class=\"h_17d pp wp-block-amp-advancedheading\" style=\"color:#fff;margin-top:10px;margin-bottom:0px\">The creative concept determines the typical behavioral targeting. The fact is that the brand is non-trivial. True, experts say that corporate identity is not so obvious.</p>\n<!-- /wp:amp/advancedheading --></div></div>\n<!-- /wp:amp/column --></div></div></div>\n<!-- /wp:amp/rowlayout --></div></div>\n<!-- /wp:amp/column --></div></div></div>\n<!-- /wp:amp/rowlayout --></div></div>\n<!-- /wp:amp/column --></div></div></div>\n<!-- /wp:amp/rowlayout --></div></div>\n<!-- /wp:amp/column --></div></div></div>\n<!-- /wp:amp/rowlayout -->"
}